lazycodr/__init__.py
lazycodr/cli/__init__.py
lazycodr/cli/config.py
lazycodr/cli/pr.py
lazycodr/cli/readme.py
lazycodr/constants.py
lazycodr/prompts/__init__.py
lazycodr/prompts/templates/pr/pr-generate-refine-init.prompt
lazycodr/prompts/templates/pr/pr-generate-refine-loop.prompt
lazycodr/prompts/templates/readme/readme-file-generate.prompt
lazycodr/prompts/templates/readme/readme-file-summary-refine-init.prompt
lazycodr/prompts/templates/readme/readme-file-summary-refine-loop.prompt
lazycodr/utils/__init__.py
lazycodr/utils/credentials.py
lazycodr/utils/pr.py
lazycodr/utils/readme.py
lazycodr-0.2.3.dist-info/METADATA
lazycodr-0.2.3.dist-info/WHEEL
lazycodr-0.2.3.dist-info/entry_points.txt
lazycodr-0.2.3.dist-info/RECORD
