Metadata-Version: 2.1
Name: lazycodr
Version: 0.2.3
Summary: A CLI tool to help lazy coders get the work done with AI (commit messages, pull requests ...)
Home-page: https://gprithub.com/bitswired/lazycodr
Author: JimZer
Author-email: jimi.vaubien@protonmail.com
Requires-Python: >=3.10,<4.0
Classifier: Programming Language :: Python :: 3
Classifier: Programming Language :: Python :: 3.10
Classifier: Programming Language :: Python :: 3.11
Classifier: Programming Language :: Python :: 3.12
Requires-Dist: httpx (>=0.24.0,<0.25.0)
Requires-Dist: jinja2 (>=3.1.2,<4.0.0)
Requires-Dist: langchain (>=0.0.325,<0.0.326)
Requires-Dist: openai (>=0.28.1,<0.29.0)
Requires-Dist: pathspec (>=0.11.2,<0.12.0)
Requires-Dist: pyfiglet (>=1.0.2,<2.0.0)
Requires-Dist: pygithub (>=2.1.1,<3.0.0)
Requires-Dist: rich (>=13.6.0,<14.0.0)
Requires-Dist: tiktoken (>=0.4.0,<0.5.0)
Requires-Dist: tqdm (>=4.66.1,<5.0.0)
Requires-Dist: typer[all] (>=0.9.0,<0.10.0)
Project-URL: Repository, https://github.com/bitswired/lazycodr
